odoo/addons/shopinvader_search_engine/README.rst
odoo/addons/shopinvader_search_engine/__init__.py
odoo/addons/shopinvader_search_engine/__manifest__.py
odoo/addons/shopinvader_search_engine/data/queue_job_function_data.xml
odoo/addons/shopinvader_search_engine/i18n/shopinvader_search_engine.pot
odoo/addons/shopinvader_search_engine/models/__init__.py
odoo/addons/shopinvader_search_engine/models/se_index.py
odoo/addons/shopinvader_search_engine/models/shopinvader_backend.py
odoo/addons/shopinvader_search_engine/models/shopinvader_category.py
odoo/addons/shopinvader_search_engine/models/shopinvader_se_binding.py
odoo/addons/shopinvader_search_engine/models/shopinvader_variant.py
odoo/addons/shopinvader_search_engine/readme/CONFIGURATION.rst
odoo/addons/shopinvader_search_engine/readme/CONTRIBUTORS.rst
odoo/addons/shopinvader_search_engine/readme/CREDITS.rst
odoo/addons/shopinvader_search_engine/readme/DESCRIPTION.rst
odoo/addons/shopinvader_search_engine/readme/HISTORY.rst
odoo/addons/shopinvader_search_engine/readme/ROADMAP.rst
odoo/addons/shopinvader_search_engine/readme/USAGE.rst
odoo/addons/shopinvader_search_engine/static/description/index.html
odoo/addons/shopinvader_search_engine/tests/__init__.py
odoo/addons/shopinvader_search_engine/tests/test_action_server.py
odoo/addons/shopinvader_search_engine/tests/test_backend.py
odoo/addons/shopinvader_search_engine/tests/test_delete_product.py
odoo/addons/shopinvader_search_engine/views/shopinvader_backend_view.xml
odoo/addons/shopinvader_search_engine/views/shopinvader_category_view.xml
odoo/addons/shopinvader_search_engine/views/shopinvader_variant_view.xml
odoo14_addon_shopinvader_search_engine-14.0.1.4.1.dist-info/METADATA
odoo14_addon_shopinvader_search_engine-14.0.1.4.1.dist-info/WHEEL
odoo14_addon_shopinvader_search_engine-14.0.1.4.1.dist-info/top_level.txt
odoo14_addon_shopinvader_search_engine-14.0.1.4.1.dist-info/RECORD
