Metadata-Version: 2.1
Name: odoo14-addon-shopinvader-search-engine
Version: 14.0.1.4.1
Summary: Shopinvader Catalog Search Engine Connector
Home-page: https://github.com/shopinvader/odoo-shopinvader
Author: Akretion
License: AGPL-3
Platform: UNKNOWN
Classifier: Programming Language :: Python
Classifier: Framework :: Odoo
Classifier: Framework :: Odoo :: 14.0
Classifier: License :: OSI Approved :: GNU Affero General Public License v3
Classifier: Development Status :: 5 - Production/Stable
Requires-Python: >=3.6
Requires-Dist: odoo14-addon-base-technical-user
Requires-Dist: odoo14-addon-connector-search-engine
Requires-Dist: odoo14-addon-shopinvader
Requires-Dist: odoo (<14.1dev,>=14.0a)
